{
	"id": "e4739d41-3ec1-47a8-ac04-468f1f41a6ba",
	"name": "Mapo-DOM",
	"values": [
		{
			"key": "BASE_URL",
			"value": "https://taas-test-api.cloud.tanium.com",
			"enabled": true
		},
		{
			"key": "SERVER_NAME",
			"value": "taas-test.cloud.tanium.com",
			"enabled": true
		},
		{
			"key": "USER_NAME",
			"value": "andy.elmaghraby@tanium.com",
			"enabled": true
		},
		{
			"key": "PASSWORD",
			"value": "P4ssw0rd_1234",
			"enabled": true
		},
		{
			"key": "API_TOKEN",
			"value": "token-5aa4deb652d4de044fa59f576a6adde33d24fb8670700a1ed321a1105d",
			"type": "default",
			"enabled": true
		},
		{
			"key": "API_KEY",
			"value": "session",
			"enabled": true
		},
		{
			"key": "ACTIONS_ENDPOINT",
			"value": "/api/v2/actions/",
			"type": "default",
			"enabled": true
		},
		{
			"key": "ACTION_GROUPS_ENDPOINT",
			"value": "/api/v2/action_groups/",
			"type": "default",
			"enabled": true
		},
		{
			"key": "GROUPS_ENDPOINT",
			"value": "/api/v2/groups/",
			"type": "default",
			"enabled": true
		},
		{
			"key": "QUESTION_ENDPOINT",
			"value": "/api/v2/questions/",
			"enabled": true
		},
		{
			"key": "PACKAGES_ENDPOINT",
			"value": "/api/v2/packages/by-name/",
			"type": "default",
			"enabled": true
		},
		{
			"key": "PARSE_QUESTION_ENDPOINT",
			"value": "/api/v2/parse_question/",
			"type": "default",
			"enabled": true
		},
		{
			"key": "RESULTS_ENDPOINT",
			"value": "/api/v2/result_data/action/",
			"type": "default",
			"enabled": true
		},
		{
			"key": "SENSOR_BY_NAME_ENDPOINT",
			"value": "/api/v2/sensors/by-name/",
			"type": "default",
			"enabled": true
		},
		{
			"key": "action_group",
			"value": "Computer Name from all machines with Reveal - Confirmed Files[2,100]:Confirmed Hits?type=NumericInteger > 0",
			"type": "default",
			"enabled": true
		},
		{
			"key": "action_group_id",
			"value": "{{body.data.id}}",
			"type": "default",
			"enabled": true
		},
		{
			"key": "package",
			"value": "content2file",
			"type": "default",
			"enabled": true
		},
		{
			"key": "question",
			"value": "\"Get Computer Name from all machines\"",
			"type": "default",
			"enabled": true
		},
		{
			"key": "questionJson",
			"value": "{\"text\": {{question}} }",
			"enabled": true
		},
		{
			"key": "target_question",
			"value": "Computer Name from all machines",
			"type": "default",
			"enabled": true
		},
		{
			"key": "target",
			"value": "endpoint",
			"type": "default",
			"enabled": true
		}
	],
	"_postman_variable_scope": "environment",
	"_postman_exported_at": "2023-03-06T20:55:09.627Z",
	"_postman_exported_using": "Postman/9.31.27"
}